easylabel/__init__.py
easylabel/corpus.py
easylabel/document.py
easylabel/py.typed
easylabel-1.3.0.dist-info/LICENSE.md
easylabel-1.3.0.dist-info/WHEEL
easylabel-1.3.0.dist-info/METADATA
easylabel-1.3.0.dist-info/RECORD
