Metadata-Version: 2.1
Name: easylabel
Version: 1.3.0
Summary: Interface for simple NER labeling
License: MIT
Author: proprefenetre
Author-email: proprefenetre@gmail.com
Requires-Python: >=3.7,<4.0
Classifier: License :: OSI Approved :: MIT License
Classifier: Programming Language :: Python :: 3
Classifier: Programming Language :: Python :: 3.7
Classifier: Programming Language :: Python :: 3.8
